empire_core/__init__.py
empire_core/accounts.py
empire_core/config.py
empire_core/exceptions.py
empire_core/pool.py
empire_core/_archive/actions.py
empire_core/_archive/cli.py
empire_core/_archive/client_async.py
empire_core/_archive/commands.py
empire_core/_archive/connection_async.py
empire_core/_archive/defense.py
empire_core/_archive/automation/__init__.py
empire_core/_archive/automation/alliance_tools.py
empire_core/_archive/automation/battle_reports.py
empire_core/_archive/automation/building_queue.py
empire_core/_archive/automation/defense_manager.py
empire_core/_archive/automation/map_scanner.py
empire_core/_archive/automation/multi_account.py
empire_core/_archive/automation/quest_automation.py
empire_core/_archive/automation/resource_manager.py
empire_core/_archive/automation/target_finder.py
empire_core/_archive/automation/tasks.py
empire_core/_archive/automation/unit_production.py
empire_core/_archive/events/__init__.py
empire_core/_archive/events/base.py
empire_core/_archive/events/manager.py
empire_core/client/__init__.py
empire_core/client/client.py
empire_core/network/__init__.py
empire_core/network/connection.py
empire_core/protocol/__init__.py
empire_core/protocol/errors.py
empire_core/protocol/packet.py
empire_core/protocol/models/__init__.py
empire_core/protocol/models/alliance.py
empire_core/protocol/models/army.py
empire_core/protocol/models/attack.py
empire_core/protocol/models/auth.py
empire_core/protocol/models/base.py
empire_core/protocol/models/building.py
empire_core/protocol/models/castle.py
empire_core/protocol/models/chat.py
empire_core/protocol/models/defense.py
empire_core/protocol/models/inventory.py
empire_core/protocol/models/lords.py
empire_core/protocol/models/map.py
empire_core/protocol/models/player.py
empire_core/protocol/models/search.py
empire_core/services/__init__.py
empire_core/services/alliance.py
empire_core/services/army.py
empire_core/services/base.py
empire_core/services/castle.py
empire_core/services/lords.py
empire_core-0.21.0.dist-info/METADATA
empire_core-0.21.0.dist-info/WHEEL
empire_core-0.21.0.dist-info/RECORD
