Metadata-Version: 2.4
Name: empire-core
Version: 0.21.0
Summary: Fully typed Python API for Goodgame Empire
Project-URL: Repository, https://github.com/eschnitzler/EmpireCore
Author-email: E Joseph <east1499@gmail.com>
License: MIT
Requires-Python: >=3.10
Requires-Dist: aiohttp>=3.9
Requires-Dist: aiosqlite>=0.19.0
Requires-Dist: pydantic>=2.5
Requires-Dist: python-dotenv>=1.0
Requires-Dist: sqlmodel>=0.0.14
Requires-Dist: tabulate>=0.9.0
Requires-Dist: tqdm>=4.66.0
Requires-Dist: typer>=0.9.0
Requires-Dist: websocket-client>=1.9.0
Provides-Extra: dev
Requires-Dist: mypy>=1.8; extra == 'dev'
Requires-Dist: pre-commit>=3.5.0; extra == 'dev'
Requires-Dist: pytest-asyncio>=0.23; extra == 'dev'
Requires-Dist: pytest>=7.0; extra == 'dev'
Requires-Dist: python-semantic-release>=9.0.0; extra == 'dev'
Requires-Dist: ruff>=0.1.0; extra == 'dev'
Requires-Dist: sqlalchemy[mypy]; extra == 'dev'
Requires-Dist: types-requests; extra == 'dev'
Requires-Dist: types-tabulate; extra == 'dev'
